curmit/__init__.py
curmit/curmit.py
curmit/test/__init__.py
curmit/test/test_cli.py
curmit-1.0.dist-info/DESCRIPTION.rst
curmit-1.0.dist-info/METADATA
curmit-1.0.dist-info/RECORD
curmit-1.0.dist-info/WHEEL
curmit-1.0.dist-info/entry_points.txt
curmit-1.0.dist-info/metadata.json
curmit-1.0.dist-info/top_level.txt
tests/__init__.py
tests/test_all.py
