Metadata-Version: 2.0
Name: curmit
Version: 1.0
Summary: Grabs text from a URL and commits it.
Home-page: https://github.com/jacebrowning/curmit
Author: Jace Browning
Author-email: jacebrowning@gmail.com
License: MIT
Platform: UNKNOWN
Classifier: Development Status :: 5 - Production/Stable
Classifier: Environment :: Console
Classifier: License :: OSI Approved :: MIT License
Classifier: Natural Language :: English
Classifier: Operating System :: OS Independent
Classifier: Programming Language :: Python
Classifier: Programming Language :: Python :: 3
Classifier: Programming Language :: Python :: 3.3
Classifier: Programming Language :: Python :: 3.4
Classifier: Programming Language :: Python :: 3.5
Classifier: Topic :: Software Development :: Documentation
Classifier: Topic :: Software Development :: Version Control
Requires-Dist: html2text (==2015.2.18)
